{
  "text": "く",
  "strokes": [
    [
      {
        "x": 0.6504854368868884,
        "y": 0.028301886792319333,
        "time": 0.001,
        "isTouching": 1
      }
    ],
    [
      {
        "x": 0.6504854368868884,
        "y": 0.028301886792319333,
        "time": 0.001,
        "isTouching": 1
      },
      {
        "x": 0.6504854368868884,
        "y": 0.02358490566026611,
        "time": 0.03112840466920014,
        "isTouching": 1
      },
      {
        "x": 0.6504854368868884,
        "y": 0.02358490566026611,
        "time": 0.03112840466920014,
        "isTouching": 1
      },
      {
        "x": 0.6601941747508718,
        "y": 0.004716981132053222,
        "time": 0.03696498054467517,
        "isTouching": 1
      },
      {
        "x": 0.6601941747508718,
        "y": 0.004716981132053222,
        "time": 0.03696498054467517,
        "isTouching": 1
      },
      {
        "x": 0.6699029126148552,
        "y": 0.0,
        "time": 0.05836575875480689,
        "isTouching": 1
      },
      {
        "x": 0.6699029126148552,
        "y": 0.0,
        "time": 0.05836575875480689,
        "isTouching": 1
      },
      {
        "x": 0.6796116504788386,
        "y": 0.0,
        "time": 0.12451361867680057,
        "isTouching": 1
      },
      {
        "x": 0.6796116504788386,
        "y": 0.0,
        "time": 0.12451361867680057,
        "isTouching": 1
      },
      {
        "x": 0.6699029126148552,
        "y": 0.014150943396159667,
        "time": 0.1556420233460007,
        "isTouching": 1
      },
      {
        "x": 0.6699029126148552,
        "y": 0.014150943396159667,
        "time": 0.1556420233460007,
        "isTouching": 1
      },
      {
        "x": 0.6699029126148552,
        "y": 0.014150943396159667,
        "time": 0.1556420233460007,
        "isTouching": 1
      },
      {
        "x": 0.6504854368868884,
        "y": 0.042452830188479,
        "time": 0.18871595330702584,
        "isTouching": 1
      },
      {
        "x": 0.6504854368868884,
        "y": 0.042452830188479,
        "time": 0.18871595330702584,
        "isTouching": 1
      },
      {
        "x": 0.6504854368868884,
        "y": 0.042452830188479,
        "time": 0.18871595330702584,
        "isTouching": 1
      },
      {
        "x": 0.5825242718390046,
        "y": 0.09905660377311766,
        "time": 0.221789883268051,
        "isTouching": 1
      },
      {
        "x": 0.5825242718390046,
        "y": 0.09905660377311766,
        "time": 0.221789883268051,
        "isTouching": 1
      },
      {
        "x": 0.5825242718390046,
        "y": 0.09905660377311766,
        "time": 0.221789883268051,
        "isTouching": 1
      },
      {
        "x": 0.45631067960722027,
        "y": 0.18867924528212887,
        "time": 0.25291828793725113,
        "isTouching": 1
      },
      {
        "x": 0.45631067960722027,
        "y": 0.18867924528212887,
        "time": 0.25486381322907614,
        "isTouching": 1
      },
      {
        "x": 0.3398058252394193,
        "y": 0.2735849056590869,
        "time": 0.2859922178982763,
        "isTouching": 1
      },
      {
        "x": 0.3398058252394193,
        "y": 0.2735849056590869,
        "time": 0.2859922178982763,
        "isTouching": 1
      },
      {
        "x": 0.23300970873560184,
        "y": 0.3349056603757788,
        "time": 0.31906614785930143,
        "isTouching": 1
      },
      {
        "x": 0.23300970873560184,
        "y": 0.3349056603757788,
        "time": 0.31906614785930143,
        "isTouching": 1
      },
      {
        "x": 0.14563106795975114,
        "y": 0.39622641509247064,
        "time": 0.35019455252850157,
        "isTouching": 1
      },
      {
        "x": 0.14563106795975114,
        "y": 0.39622641509247064,
        "time": 0.35019455252850157,
        "isTouching": 1
      },
      {
        "x": 0.07766990291186728,
        "y": 0.43396226414889644,
        "time": 0.38326848248958334,
        "isTouching": 1
      },
      {
        "x": 0.07766990291186728,
        "y": 0.43396226414889644,
        "time": 0.38326848248958334,
        "isTouching": 1
      },
      {
        "x": 0.07766990291186728,
        "y": 0.43396226414889644,
        "time": 0.38326848248958334,
        "isTouching": 1
      },
      {
        "x": 0.02912621359195023,
        "y": 0.45754716980916255,
        "time": 0.41439688715872686,
        "isTouching": 1
      },
      {
        "x": 0.02912621359195023,
        "y": 0.45754716980916255,
        "time": 0.41634241245055187,
        "isTouching": 1
      },
      {
        "x": 0.02912621359195023,
        "y": 0.45754716980916255,
        "time": 0.41634241245055187,
        "isTouching": 1
      },
      {
        "x": 0.0,
        "y": 0.47641509433737544,
        "time": 0.447470817119752,
        "isTouching": 1
      },
      {
        "x": 0.0,
        "y": 0.47641509433737544,
        "time": 0.447470817119752,
        "isTouching": 1
      },
      {
        "x": 0.0,
        "y": 0.47641509433737544,
        "time": 0.447470817119752,
        "isTouching": 1
      },
      {
        "x": 0.0,
        "y": 0.48584905660148187,
        "time": 0.48054474708077716,
        "isTouching": 1
      },
      {
        "x": 0.0,
        "y": 0.48584905660148187,
        "time": 0.48054474708077716,
        "isTouching": 1
      },
      {
        "x": 0.0,
        "y": 0.48584905660148187,
        "time": 0.48054474708077716,
        "isTouching": 1
      },
      {
        "x": 0.0,
        "y": 0.4952830188655883,
        "time": 0.5116731517499773,
        "isTouching": 1
      },
      {
        "x": 0.0,
        "y": 0.4952830188655883,
        "time": 0.5116731517499773,
        "isTouching": 1
      },
      {
        "x": 0.0,
        "y": 0.4952830188655883,
        "time": 0.5116731517499773,
        "isTouching": 1
      },
      {
        "x": 0.03883495145593364,
        "y": 0.509433962261748,
        "time": 0.5447470817110591,
        "isTouching": 1
      },
      {
        "x": 0.03883495145593364,
        "y": 0.509433962261748,
        "time": 0.5447470817110591,
        "isTouching": 1
      },
      {
        "x": 0.03883495145593364,
        "y": 0.509433962261748,
        "time": 0.5447470817110591,
        "isTouching": 1
      },
      {
        "x": 0.08737864077585068,
        "y": 0.5283018867899608,
        "time": 0.5778210116720276,
        "isTouching": 1
      },
      {
        "x": 0.08737864077585068,
        "y": 0.5283018867899608,
        "time": 0.5778210116720276,
        "isTouching": 1
      },
      {
        "x": 0.08737864077585068,
        "y": 0.5283018867899608,
        "time": 0.5778210116720276,
        "isTouching": 1
      },
      {
        "x": 0.15533980582373455,
        "y": 0.5566037735822802,
        "time": 0.6089494163412278,
        "isTouching": 1
      },
      {
        "x": 0.15533980582373455,
        "y": 0.5566037735822802,
        "time": 0.6089494163412278,
        "isTouching": 1
      },
      {
        "x": 0.15533980582373455,
        "y": 0.5566037735822802,
        "time": 0.6089494163412278,
        "isTouching": 1
      },
      {
        "x": 0.24271844659958525,
        "y": 0.5896226415066528,
        "time": 0.6420233463022529,
        "isTouching": 1
      },
      {
        "x": 0.24271844659958525,
        "y": 0.5896226415066528,
        "time": 0.6420233463022529,
        "isTouching": 1
      },
      {
        "x": 0.24271844659958525,
        "y": 0.5896226415066528,
        "time": 0.6420233463022529,
        "isTouching": 1
      },
      {
        "x": 0.3592233009673862,
        "y": 0.6415094339592382,
        "time": 0.6750972762632781,
        "isTouching": 1
      },
      {
        "x": 0.3592233009673862,
        "y": 0.6415094339592382,
        "time": 0.6750972762632781,
        "isTouching": 1
      },
      {
        "x": 0.3592233009673862,
        "y": 0.6415094339592382,
        "time": 0.6750972762632781,
        "isTouching": 1
      },
      {
        "x": 0.4660194174712037,
        "y": 0.6933962264118236,
        "time": 0.7062256809324782,
        "isTouching": 1
      },
      {
        "x": 0.4660194174712037,
        "y": 0.6933962264118236,
        "time": 0.7062256809324782,
        "isTouching": 1
      },
      {
        "x": 0.4660194174712037,
        "y": 0.6933962264118236,
        "time": 0.7062256809324782,
        "isTouching": 1
      },
      {
        "x": 0.5825242718390046,
        "y": 0.7452830188644091,
        "time": 0.7392996108935034,
        "isTouching": 1
      },
      {
        "x": 0.5825242718390046,
        "y": 0.7452830188644091,
        "time": 0.7392996108935034,
        "isTouching": 1
      },
      {
        "x": 0.5825242718390046,
        "y": 0.7452830188644091,
        "time": 0.7392996108935034,
        "isTouching": 1
      },
      {
        "x": 0.6796116504788386,
        "y": 0.8018867924490477,
        "time": 0.7723735408545285,
        "isTouching": 1
      },
      {
        "x": 0.6796116504788386,
        "y": 0.8018867924490477,
        "time": 0.7723735408545285,
        "isTouching": 1
      },
      {
        "x": 0.6796116504788386,
        "y": 0.8018867924490477,
        "time": 0.7723735408545285,
        "isTouching": 1
      },
      {
        "x": 0.7864077669826562,
        "y": 0.8537735849016331,
        "time": 0.8054474708155536,
        "isTouching": 1
      },
      {
        "x": 0.7864077669826562,
        "y": 0.8537735849016331,
        "time": 0.8054474708155536,
        "isTouching": 1
      },
      {
        "x": 0.7864077669826562,
        "y": 0.8537735849016331,
        "time": 0.8054474708155536,
        "isTouching": 1
      },
      {
        "x": 0.8737864077585069,
        "y": 0.9056603773542187,
        "time": 0.8365758754847538,
        "isTouching": 1
      },
      {
        "x": 0.8737864077585069,
        "y": 0.9056603773542187,
        "time": 0.8365758754847538,
        "isTouching": 1
      },
      {
        "x": 0.8737864077585069,
        "y": 0.9056603773542187,
        "time": 0.8365758754847538,
        "isTouching": 1
      },
      {
        "x": 0.9320388349424074,
        "y": 0.9433962264106444,
        "time": 0.8696498054458355,
        "isTouching": 1
      },
      {
        "x": 0.9320388349424074,
        "y": 0.9433962264106444,
        "time": 0.8696498054458355,
        "isTouching": 1
      },
      {
        "x": 0.9320388349424074,
        "y": 0.9433962264106444,
        "time": 0.8696498054458355,
        "isTouching": 1
      },
      {
        "x": 0.9805825242623244,
        "y": 0.9716981132029637,
        "time": 0.900778210114979,
        "isTouching": 1
      },
      {
        "x": 0.9805825242623244,
        "y": 0.9716981132029637,
        "time": 0.9027237354068041,
        "isTouching": 1
      },
      {
        "x": 0.9805825242623244,
        "y": 0.9716981132029637,
        "time": 0.9027237354068041,
        "isTouching": 1
      },
      {
        "x": 0.9999999999902912,
        "y": 0.9905660377311766,
        "time": 0.9338521400760041,
        "isTouching": 1
      },
      {
        "x": 0.9999999999902912,
        "y": 0.9905660377311766,
        "time": 0.9338521400760041,
        "isTouching": 1
      },
      {
        "x": 0.9999999999902912,
        "y": 0.9905660377311766,
        "time": 0.9338521400760041,
        "isTouching": 1
      },
      {
        "x": 0.9999999999902912,
        "y": 0.9952830188632299,
        "time": 0.9669260700370294,
        "isTouching": 1
      },
      {
        "x": 0.9999999999902912,
        "y": 0.9952830188632299,
        "time": 0.9669260700370294,
        "isTouching": 1
      },
      {
        "x": 0.9999999999902912,
        "y": 0.9952830188632299,
        "time": 0.9669260700370294,
        "isTouching": 1
      },
      {
        "x": 0.9999999999902912,
        "y": 0.9999999999952831,
        "time": 0.9980544747062294,
        "isTouching": 1
      },
      {
        "x": 0.9999999999902912,
        "y": 0.9999999999952831,
        "time": 0.9980544747062294,
        "isTouching": 1
      },
      {
        "x": 0.9999999999902912,
        "y": 0.9999999999952831,
        "time": 0.9980544747062294,
        "isTouching": 1
      },
      {
        "x": 0.9902912621263078,
        "y": 0.9999999999952831,
        "time": 0.9999999999980544,
        "isTouching": 0
      }
    ]
  ],
  "filename": "く_20250924141742.json"
}