{
  "text": "え",
  "strokes": [
    [
      {
        "x": 345,
        "y": 71.125,
        "time": 0,
        "isTouching": 1
      }
    ],
    [
      {
        "x": 345,
        "y": 71.125,
        "time": 0,
        "isTouching": 1
      },
      {
        "x": 345,
        "y": 69.125,
        "time": 14,
        "isTouching": 1
      },
      {
        "x": 345,
        "y": 69.125,
        "time": 14,
        "isTouching": 1
      },
      {
        "x": 346,
        "y": 69.125,
        "time": 16.000000000014552,
        "isTouching": 1
      },
      {
        "x": 346,
        "y": 69.125,
        "time": 16.000000000014552,
        "isTouching": 1
      },
      {
        "x": 348,
        "y": 70.125,
        "time": 30,
        "isTouching": 1
      },
      {
        "x": 348,
        "y": 70.125,
        "time": 30,
        "isTouching": 1
      },
      {
        "x": 352,
        "y": 73.125,
        "time": 47,
        "isTouching": 1
      },
      {
        "x": 352,
        "y": 73.125,
        "time": 47,
        "isTouching": 1
      },
      {
        "x": 359,
        "y": 77.125,
        "time": 64,
        "isTouching": 1
      },
      {
        "x": 359,
        "y": 77.125,
        "time": 64,
        "isTouching": 1
      },
      {
        "x": 366,
        "y": 78.125,
        "time": 80,
        "isTouching": 1
      },
      {
        "x": 366,
        "y": 78.125,
        "time": 80,
        "isTouching": 1
      },
      {
        "x": 372,
        "y": 79.125,
        "time": 97,
        "isTouching": 1
      },
      {
        "x": 372,
        "y": 79.125,
        "time": 97,
        "isTouching": 1
      },
      {
        "x": 374,
        "y": 79.125,
        "time": 113,
        "isTouching": 0
      }
    ],
    [
      {
        "x": 335,
        "y": 119.125,
        "time": 0,
        "isTouching": 1
      }
    ],
    [
      {
        "x": 335,
        "y": 119.125,
        "time": 0,
        "isTouching": 1
      },
      {
        "x": 335,
        "y": 118.125,
        "time": 17,
        "isTouching": 1
      },
      {
        "x": 335,
        "y": 118.125,
        "time": 17,
        "isTouching": 1
      },
      {
        "x": 336,
        "y": 117.125,
        "time": 29,
        "isTouching": 1
      },
      {
        "x": 336,
        "y": 117.125,
        "time": 30.000000000014552,
        "isTouching": 1
      },
      {
        "x": 341,
        "y": 114.125,
        "time": 46,
        "isTouching": 1
      },
      {
        "x": 341,
        "y": 114.125,
        "time": 46,
        "isTouching": 1
      },
      {
        "x": 348,
        "y": 110.125,
        "time": 63,
        "isTouching": 1
      },
      {
        "x": 348,
        "y": 110.125,
        "time": 63,
        "isTouching": 1
      },
      {
        "x": 358,
        "y": 104.125,
        "time": 80,
        "isTouching": 1
      },
      {
        "x": 358,
        "y": 104.125,
        "time": 80,
        "isTouching": 1
      },
      {
        "x": 366,
        "y": 101.125,
        "time": 96,
        "isTouching": 1
      },
      {
        "x": 366,
        "y": 101.125,
        "time": 96,
        "isTouching": 1
      },
      {
        "x": 370,
        "y": 99.125,
        "time": 113,
        "isTouching": 1
      },
      {
        "x": 370,
        "y": 99.125,
        "time": 113,
        "isTouching": 1
      },
      {
        "x": 372,
        "y": 99.125,
        "time": 130,
        "isTouching": 1
      },
      {
        "x": 372,
        "y": 99.125,
        "time": 130,
        "isTouching": 1
      },
      {
        "x": 373,
        "y": 99.125,
        "time": 146.00000000001455,
        "isTouching": 1
      },
      {
        "x": 373,
        "y": 99.125,
        "time": 146.00000000001455,
        "isTouching": 1
      },
      {
        "x": 373,
        "y": 99.125,
        "time": 146.00000000001455,
        "isTouching": 1
      },
      {
        "x": 373,
        "y": 99.125,
        "time": 163,
        "isTouching": 1
      },
      {
        "x": 373,
        "y": 99.125,
        "time": 180,
        "isTouching": 1
      },
      {
        "x": 373,
        "y": 100.125,
        "time": 196,
        "isTouching": 1
      },
      {
        "x": 373,
        "y": 100.125,
        "time": 196,
        "isTouching": 1
      },
      {
        "x": 373,
        "y": 100.125,
        "time": 196,
        "isTouching": 1
      },
      {
        "x": 371,
        "y": 103.125,
        "time": 213,
        "isTouching": 1
      },
      {
        "x": 371,
        "y": 103.125,
        "time": 213,
        "isTouching": 1
      },
      {
        "x": 371,
        "y": 103.125,
        "time": 213,
        "isTouching": 1
      },
      {
        "x": 368,
        "y": 109.125,
        "time": 230,
        "isTouching": 1
      },
      {
        "x": 368,
        "y": 109.125,
        "time": 230,
        "isTouching": 1
      },
      {
        "x": 368,
        "y": 109.125,
        "time": 230,
        "isTouching": 1
      },
      {
        "x": 364,
        "y": 117.125,
        "time": 246,
        "isTouching": 1
      },
      {
        "x": 364,
        "y": 117.125,
        "time": 246,
        "isTouching": 1
      },
      {
        "x": 357,
        "y": 128.125,
        "time": 263,
        "isTouching": 1
      },
      {
        "x": 357,
        "y": 128.125,
        "time": 263,
        "isTouching": 1
      },
      {
        "x": 350,
        "y": 141.125,
        "time": 280.00000000001455,
        "isTouching": 1
      },
      {
        "x": 350,
        "y": 141.125,
        "time": 280.00000000001455,
        "isTouching": 1
      },
      {
        "x": 344,
        "y": 153.125,
        "time": 296,
        "isTouching": 1
      },
      {
        "x": 344,
        "y": 153.125,
        "time": 296,
        "isTouching": 1
      },
      {
        "x": 337,
        "y": 167.125,
        "time": 313,
        "isTouching": 1
      },
      {
        "x": 337,
        "y": 167.125,
        "time": 313,
        "isTouching": 1
      },
      {
        "x": 333,
        "y": 175.125,
        "time": 330,
        "isTouching": 1
      },
      {
        "x": 333,
        "y": 175.125,
        "time": 330,
        "isTouching": 1
      },
      {
        "x": 333,
        "y": 175.125,
        "time": 330,
        "isTouching": 1
      },
      {
        "x": 331,
        "y": 178.125,
        "time": 346,
        "isTouching": 1
      },
      {
        "x": 331,
        "y": 178.125,
        "time": 346,
        "isTouching": 1
      },
      {
        "x": 331,
        "y": 178.125,
        "time": 346,
        "isTouching": 1
      },
      {
        "x": 331,
        "y": 178.125,
        "time": 363,
        "isTouching": 1
      },
      {
        "x": 331,
        "y": 177.125,
        "time": 380,
        "isTouching": 1
      },
      {
        "x": 331,
        "y": 177.125,
        "time": 380,
        "isTouching": 1
      },
      {
        "x": 331,
        "y": 177.125,
        "time": 380,
        "isTouching": 1
      },
      {
        "x": 331,
        "y": 173.125,
        "time": 396.00000000001455,
        "isTouching": 1
      },
      {
        "x": 331,
        "y": 173.125,
        "time": 396.00000000001455,
        "isTouching": 1
      },
      {
        "x": 331,
        "y": 173.125,
        "time": 396.00000000001455,
        "isTouching": 1
      },
      {
        "x": 332,
        "y": 167.125,
        "time": 413,
        "isTouching": 1
      },
      {
        "x": 332,
        "y": 167.125,
        "time": 413,
        "isTouching": 1
      },
      {
        "x": 332,
        "y": 167.125,
        "time": 413,
        "isTouching": 1
      },
      {
        "x": 335,
        "y": 161.125,
        "time": 430,
        "isTouching": 1
      },
      {
        "x": 335,
        "y": 161.125,
        "time": 430,
        "isTouching": 1
      },
      {
        "x": 338,
        "y": 155.125,
        "time": 446,
        "isTouching": 1
      },
      {
        "x": 338,
        "y": 155.125,
        "time": 446,
        "isTouching": 1
      },
      {
        "x": 343,
        "y": 150.125,
        "time": 463,
        "isTouching": 1
      },
      {
        "x": 343,
        "y": 150.125,
        "time": 463,
        "isTouching": 1
      },
      {
        "x": 347,
        "y": 148.125,
        "time": 479,
        "isTouching": 1
      },
      {
        "x": 347,
        "y": 148.125,
        "time": 480,
        "isTouching": 1
      },
      {
        "x": 350,
        "y": 148.125,
        "time": 496,
        "isTouching": 1
      },
      {
        "x": 350,
        "y": 148.125,
        "time": 496,
        "isTouching": 1
      },
      {
        "x": 353,
        "y": 149.125,
        "time": 513,
        "isTouching": 1
      },
      {
        "x": 353,
        "y": 149.125,
        "time": 513,
        "isTouching": 1
      },
      {
        "x": 356,
        "y": 151.125,
        "time": 530.0000000000146,
        "isTouching": 1
      },
      {
        "x": 356,
        "y": 151.125,
        "time": 530.0000000000146,
        "isTouching": 1
      },
      {
        "x": 358,
        "y": 152.125,
        "time": 546,
        "isTouching": 1
      },
      {
        "x": 358,
        "y": 152.125,
        "time": 546,
        "isTouching": 1
      },
      {
        "x": 361,
        "y": 156.125,
        "time": 563,
        "isTouching": 1
      },
      {
        "x": 361,
        "y": 156.125,
        "time": 563,
        "isTouching": 1
      },
      {
        "x": 362,
        "y": 161.125,
        "time": 580,
        "isTouching": 1
      },
      {
        "x": 362,
        "y": 161.125,
        "time": 580,
        "isTouching": 1
      },
      {
        "x": 364,
        "y": 168.125,
        "time": 596,
        "isTouching": 1
      },
      {
        "x": 364,
        "y": 168.125,
        "time": 596,
        "isTouching": 1
      },
      {
        "x": 367,
        "y": 173.125,
        "time": 613,
        "isTouching": 1
      },
      {
        "x": 367,
        "y": 173.125,
        "time": 613,
        "isTouching": 1
      },
      {
        "x": 373,
        "y": 175.125,
        "time": 630,
        "isTouching": 1
      },
      {
        "x": 373,
        "y": 175.125,
        "time": 630,
        "isTouching": 1
      },
      {
        "x": 379,
        "y": 174.125,
        "time": 646.0000000000146,
        "isTouching": 1
      },
      {
        "x": 379,
        "y": 174.125,
        "time": 646.0000000000146,
        "isTouching": 1
      },
      {
        "x": 387,
        "y": 170.125,
        "time": 663,
        "isTouching": 1
      },
      {
        "x": 387,
        "y": 170.125,
        "time": 663,
        "isTouching": 1
      },
      {
        "x": 397,
        "y": 162.125,
        "time": 680,
        "isTouching": 1
      },
      {
        "x": 397,
        "y": 162.125,
        "time": 680,
        "isTouching": 1
      },
      {
        "x": 406,
        "y": 153.125,
        "time": 696,
        "isTouching": 1
      },
      {
        "x": 406,
        "y": 153.125,
        "time": 696,
        "isTouching": 1
      },
      {
        "x": 411,
        "y": 150.125,
        "time": 713,
        "isTouching": 1
      },
      {
        "x": 411,
        "y": 150.125,
        "time": 713,
        "isTouching": 1
      },
      {
        "x": 413,
        "y": 150.125,
        "time": 729,
        "isTouching": 1
      },
      {
        "x": 413,
        "y": 150.125,
        "time": 730,
        "isTouching": 1
      },
      {
        "x": 412,
        "y": 151.125,
        "time": 746,
        "isTouching": 1
      },
      {
        "x": 412,
        "y": 151.125,
        "time": 746,
        "isTouching": 1
      },
      {
        "x": 411,
        "y": 151.125,
        "time": 812,
        "isTouching": 0
      }
    ]
  ],
  "filename": "え_20251002042156.json"
}