{
  "text": "て",
  "strokes": [
    [
      {
        "x": 286,
        "y": 118.125,
        "time": 0,
        "isTouching": 1
      }
    ],
    [
      {
        "x": 286,
        "y": 118.125,
        "time": 0,
        "isTouching": 1
      },
      {
        "x": 285,
        "y": 117.125,
        "time": 12.999999999883585,
        "isTouching": 1
      },
      {
        "x": 285,
        "y": 117.125,
        "time": 12.999999999883585,
        "isTouching": 1
      },
      {
        "x": 284,
        "y": 116.125,
        "time": 15.999999999883585,
        "isTouching": 1
      },
      {
        "x": 284,
        "y": 116.125,
        "time": 15.999999999883585,
        "isTouching": 1
      },
      {
        "x": 288,
        "y": 114.125,
        "time": 29.999999999883585,
        "isTouching": 1
      },
      {
        "x": 288,
        "y": 114.125,
        "time": 29.999999999883585,
        "isTouching": 1
      },
      {
        "x": 299,
        "y": 109.125,
        "time": 45.999999999883585,
        "isTouching": 1
      },
      {
        "x": 299,
        "y": 109.125,
        "time": 45.999999999883585,
        "isTouching": 1
      },
      {
        "x": 314,
        "y": 103.125,
        "time": 62.999999999883585,
        "isTouching": 1
      },
      {
        "x": 314,
        "y": 103.125,
        "time": 62.999999999883585,
        "isTouching": 1
      },
      {
        "x": 330,
        "y": 97.125,
        "time": 78.99999999988358,
        "isTouching": 1
      },
      {
        "x": 330,
        "y": 97.125,
        "time": 79.99999999988358,
        "isTouching": 1
      },
      {
        "x": 330,
        "y": 97.125,
        "time": 79.99999999988358,
        "isTouching": 1
      },
      {
        "x": 347,
        "y": 92.125,
        "time": 96,
        "isTouching": 1
      },
      {
        "x": 347,
        "y": 92.125,
        "time": 96,
        "isTouching": 1
      },
      {
        "x": 347,
        "y": 92.125,
        "time": 96,
        "isTouching": 1
      },
      {
        "x": 365,
        "y": 87.125,
        "time": 112.99999999988358,
        "isTouching": 1
      },
      {
        "x": 365,
        "y": 87.125,
        "time": 112.99999999988358,
        "isTouching": 1
      },
      {
        "x": 365,
        "y": 87.125,
        "time": 112.99999999988358,
        "isTouching": 1
      },
      {
        "x": 382,
        "y": 83.125,
        "time": 130,
        "isTouching": 1
      },
      {
        "x": 382,
        "y": 83.125,
        "time": 130,
        "isTouching": 1
      },
      {
        "x": 382,
        "y": 83.125,
        "time": 130,
        "isTouching": 1
      },
      {
        "x": 396,
        "y": 81.125,
        "time": 145.99999999988358,
        "isTouching": 1
      },
      {
        "x": 396,
        "y": 81.125,
        "time": 145.99999999988358,
        "isTouching": 1
      },
      {
        "x": 396,
        "y": 81.125,
        "time": 145.99999999988358,
        "isTouching": 1
      },
      {
        "x": 404,
        "y": 80.125,
        "time": 162.99999999988358,
        "isTouching": 1
      },
      {
        "x": 404,
        "y": 80.125,
        "time": 162.99999999988358,
        "isTouching": 1
      },
      {
        "x": 404,
        "y": 80.125,
        "time": 162.99999999988358,
        "isTouching": 1
      },
      {
        "x": 408,
        "y": 80.125,
        "time": 179.99999999988358,
        "isTouching": 1
      },
      {
        "x": 408,
        "y": 80.125,
        "time": 179.99999999988358,
        "isTouching": 1
      },
      {
        "x": 408,
        "y": 80.125,
        "time": 179.99999999988358,
        "isTouching": 1
      },
      {
        "x": 409,
        "y": 80.125,
        "time": 195.99999999988358,
        "isTouching": 1
      },
      {
        "x": 409,
        "y": 80.125,
        "time": 195.99999999988358,
        "isTouching": 1
      },
      {
        "x": 409,
        "y": 80.125,
        "time": 197,
        "isTouching": 1
      },
      {
        "x": 405,
        "y": 82.125,
        "time": 212.99999999988358,
        "isTouching": 1
      },
      {
        "x": 405,
        "y": 82.125,
        "time": 212.99999999988358,
        "isTouching": 1
      },
      {
        "x": 405,
        "y": 82.125,
        "time": 212.99999999988358,
        "isTouching": 1
      },
      {
        "x": 395,
        "y": 89.125,
        "time": 229.99999999988358,
        "isTouching": 1
      },
      {
        "x": 395,
        "y": 89.125,
        "time": 229.99999999988358,
        "isTouching": 1
      },
      {
        "x": 395,
        "y": 89.125,
        "time": 229.99999999988358,
        "isTouching": 1
      },
      {
        "x": 378,
        "y": 103.125,
        "time": 245.99999999988358,
        "isTouching": 1
      },
      {
        "x": 378,
        "y": 103.125,
        "time": 245.99999999988358,
        "isTouching": 1
      },
      {
        "x": 378,
        "y": 103.125,
        "time": 245.99999999988358,
        "isTouching": 1
      },
      {
        "x": 354,
        "y": 130.125,
        "time": 262.9999999998836,
        "isTouching": 1
      },
      {
        "x": 354,
        "y": 130.125,
        "time": 262.9999999998836,
        "isTouching": 1
      },
      {
        "x": 327,
        "y": 172.125,
        "time": 279.9999999998836,
        "isTouching": 1
      },
      {
        "x": 327,
        "y": 172.125,
        "time": 279.9999999998836,
        "isTouching": 1
      },
      {
        "x": 310,
        "y": 207.125,
        "time": 296.9999999998836,
        "isTouching": 1
      },
      {
        "x": 310,
        "y": 207.125,
        "time": 296.9999999998836,
        "isTouching": 1
      },
      {
        "x": 304,
        "y": 230.125,
        "time": 312.9999999998836,
        "isTouching": 1
      },
      {
        "x": 304,
        "y": 230.125,
        "time": 312.9999999998836,
        "isTouching": 1
      },
      {
        "x": 304,
        "y": 230.125,
        "time": 312.9999999998836,
        "isTouching": 1
      },
      {
        "x": 308,
        "y": 246.125,
        "time": 329.9999999998836,
        "isTouching": 1
      },
      {
        "x": 308,
        "y": 246.125,
        "time": 329.9999999998836,
        "isTouching": 1
      },
      {
        "x": 308,
        "y": 246.125,
        "time": 329.9999999998836,
        "isTouching": 1
      },
      {
        "x": 318,
        "y": 256.125,
        "time": 346,
        "isTouching": 1
      },
      {
        "x": 318,
        "y": 256.125,
        "time": 346,
        "isTouching": 1
      },
      {
        "x": 318,
        "y": 256.125,
        "time": 346,
        "isTouching": 1
      },
      {
        "x": 333,
        "y": 260.125,
        "time": 362.9999999998836,
        "isTouching": 1
      },
      {
        "x": 333,
        "y": 260.125,
        "time": 362.9999999998836,
        "isTouching": 1
      },
      {
        "x": 333,
        "y": 260.125,
        "time": 362.9999999998836,
        "isTouching": 1
      },
      {
        "x": 350,
        "y": 258.125,
        "time": 380,
        "isTouching": 1
      },
      {
        "x": 350,
        "y": 258.125,
        "time": 380,
        "isTouching": 1
      },
      {
        "x": 350,
        "y": 258.125,
        "time": 380,
        "isTouching": 1
      },
      {
        "x": 364,
        "y": 252.125,
        "time": 396.9999999998836,
        "isTouching": 1
      },
      {
        "x": 364,
        "y": 252.125,
        "time": 396.9999999998836,
        "isTouching": 1
      },
      {
        "x": 364,
        "y": 252.125,
        "time": 396.9999999998836,
        "isTouching": 1
      },
      {
        "x": 369,
        "y": 249.125,
        "time": 412.9999999998836,
        "isTouching": 0
      }
    ]
  ],
  "filename": "て_20251002043700.json"
}